m6rc/__init__.py
m6rc/embed_lexer.py
m6rc/m6rc.py
m6rc/metaphor_ast_node.py
m6rc/metaphor_formatters.py
m6rc/metaphor_lexer.py
m6rc/metaphor_parser.py
m6rc/metaphor_token.py
m6rc-0.7.dist-info/METADATA
m6rc-0.7.dist-info/WHEEL
m6rc-0.7.dist-info/entry_points.txt
m6rc-0.7.dist-info/licenses/LICENSE.txt
m6rc-0.7.dist-info/RECORD
