Metadata-Version: 2.4
Name: m6rc
Version: 0.7
Summary: Command line tool for compling prompts using the Metaphor format
Project-URL: Homepage, https://github.com/m6r-ai/m6rc
Project-URL: Issues, https://github.com/m6r-ai/m6rc/issues
Author-email: M6R <hello@m6r.ai>
License-File: LICENSE.txt
Classifier: License :: OSI Approved :: Apache Software License
Classifier: Operating System :: OS Independent
Classifier: Programming Language :: Python :: 3
Requires-Python: >=3.10
